bpolib.py
bpolib-0.0.6a0.dist-info/LICENSE
bpolib-0.0.6a0.dist-info/METADATA
bpolib-0.0.6a0.dist-info/WHEEL
bpolib-0.0.6a0.dist-info/top_level.txt
bpolib-0.0.6a0.dist-info/RECORD
