Metadata-Version: 2.1
Name: bpolib
Version: 0.0.6a0
Summary: -- alpha release --
Home-page: UNKNOWN
Author: Kreusada
Author-email: kreusadaprojects@gmail.com
License: UNKNOWN
Platform: UNKNOWN
License-File: LICENSE
Requires-Dist: bs4
Requires-Dist: python-dateutil
